{
  "dimensions": [
    {
      "text": "7/",
      "bbox": [
        4549,
        1024,
        148,
        222
      ],
      "confidence": 74
    },
    {
      "text": "5.5791",
      "bbox": [
        650,
        1319,
        265,
        77
      ],
      "confidence": 31
    },
    {
      "text": "4",
      "bbox": [
        3421,
        2771,
        53,
        70
      ],
      "confidence": 59
    },
    {
      "text": "03",
      "bbox": [
        4445,
        2810,
        51,
        43
      ],
      "confidence": 53
    },
    {
      "text": "4",
      "bbox": [
        1402,
        2826,
        19,
        84
      ],
      "confidence": 41
    },
    {
      "text": "5",
      "bbox": [
        2934,
        3163,
        68,
        93
      ],
      "confidence": 49
    },
    {
      "text": "9",
      "bbox": [
        572,
        3252,
        32,
        65
      ],
      "confidence": 83
    },
    {
      "text": "2",
      "bbox": [
        2267,
        3223,
        31,
        51
      ],
      "confidence": 83
    },
    {
      "text": "0",
      "bbox": [
        2321,
        3332,
        43,
        9
      ],
      "confidence": 34
    },
    {
      "text": "4",
      "bbox": [
        5877,
        3519,
        42,
        28
      ],
      "confidence": 64
    },
    {
      "text": "5",
      "bbox": [
        2673,
        3654,
        31,
        48
      ],
      "confidence": 87
    },
    {
      "text": "2",
      "bbox": [
        2673,
        3762,
        31,
        52
      ],
      "confidence": 83
    },
    {
      "text": "9",
      "bbox": [
        3905,
        3770,
        31,
        65
      ],
      "confidence": 75
    },
    {
      "text": "0",
      "bbox": [
        9259,
        3925,
        26,
        43
      ],
      "confidence": 75
    },
    {
      "text": "8",
      "bbox": [
        1869,
        4251,
        44,
        72
      ],
      "confidence": 49
    },
    {
      "text": "2",
      "bbox": [
        4084,
        4211,
        32,
        51
      ],
      "confidence": 93
    },
    {
      "text": "908",
      "bbox": [
        1076,
        4939,
        77,
        51
      ],
      "confidence": 78
    },
    {
      "text": "1.9)",
      "bbox": [
        1001,
        4992,
        175,
        140
      ],
      "confidence": 46
    },
    {
      "text": "7",
      "bbox": [
        621,
        5317,
        32,
        42
      ],
      "confidence": 48
    },
    {
      "text": "5",
      "bbox": [
        854,
        5482,
        25,
        33
      ],
      "confidence": 50
    },
    {
      "text": "4",
      "bbox": [
        5004,
        5553,
        33,
        42
      ],
      "confidence": 45
    },
    {
      "text": "0",
      "bbox": [
        830,
        5607,
        63,
        44
      ],
      "confidence": 60
    },
    {
      "text": "7",
      "bbox": [
        2962,
        5642,
        3,
        18
      ],
      "confidence": 32
    },
    {
      "text": "3.9",
      "bbox": [
        688,
        5607,
        106,
        72
      ],
      "confidence": 73
    },
    {
      "text": "1004",
      "bbox": [
        2384,
        5971,
        96,
        31
      ],
      "confidence": 95
    },
    {
      "text": "5",
      "bbox": [
        1007,
        6271,
        65,
        81
      ],
      "confidence": 91
    },
    {
      "text": "2",
      "bbox": [
        1836,
        6352,
        229,
        85
      ],
      "confidence": 69
    },
    {
      "text": "5",
      "bbox": [
        1272,
        6508,
        30,
        44
      ],
      "confidence": 87
    },
    {
      "text": "3",
      "bbox": [
        7045,
        6493,
        30,
        16
      ],
      "confidence": 68
    },
    {
      "text": "0",
      "bbox": [
        9647,
        6615,
        23,
        33
      ],
      "confidence": 67
    },
    {
      "text": "4",
      "bbox": [
        9715,
        6769,
        35,
        85
      ],
      "confidence": 63
    }
  ],
  "tolerances": [],
  "notes": [
    {
      "text": "DEL_No.",
      "bbox": [
        778,
        467,
        245,
        44
      ],
      "confidence": 58
    },
    {
      "text": "&%",
      "bbox": [
        5054,
        509,
        141,
        77
      ],
      "confidence": 48
    },
    {
      "text": ">",
      "bbox": [
        5670,
        647,
        27,
        35
      ],
      "confidence": 44
    },
    {
      "text": "Wo:",
      "bbox": [
        5094,
        732,
        72,
        36
      ],
      "confidence": 85
    },
    {
      "text": "=",
      "bbox": [
        4323,
        778,
        77,
        37
      ],
      "confidence": 59
    },
    {
      "text": "eee",
      "bbox": [
        7714,
        729,
        2098,
        103
      ],
      "confidence": 31
    },
    {
      "text": "[LR",
      "bbox": [
        4718,
        883,
        270,
        119
      ],
      "confidence": 34
    },
    {
      "text": "ASK",
      "bbox": [
        4881,
        935,
        107,
        73
      ],
      "confidence": 65
    },
    {
      "text": "y,",
      "bbox": [
        1298,
        1011,
        42,
        109
      ],
      "confidence": 51
    },
    {
      "text": "SS",
      "bbox": [
        4102,
        1120,
        96,
        46
      ],
      "confidence": 78
    },
    {
      "text": "~",
      "bbox": [
        1615,
        1169,
        42,
        51
      ],
      "confidence": 40
    },
    {
      "text": "SS",
      "bbox": [
        4210,
        1169,
        118,
        57
      ],
      "confidence": 77
    },
    {
      "text": "SS",
      "bbox": [
        4334,
        1188,
        80,
        109
      ],
      "confidence": 92
    },
    {
      "text": ")",
      "bbox": [
        4446,
        1300,
        26,
        39
      ],
      "confidence": 89
    },
    {
      "text": "(",
      "bbox": [
        199,
        1434,
        18,
        31
      ],
      "confidence": 37
    },
    {
      "text": "S>",
      "bbox": [
        4207,
        1515,
        155,
        99
      ],
      "confidence": 39
    },
    {
      "text": "|",
      "bbox": [
        3369,
        2175,
        3,
        83
      ],
      "confidence": 94
    },
    {
      "text": "B",
      "bbox": [
        1701,
        2354,
        54,
        73
      ],
      "confidence": 79
    },
    {
      "text": "Y",
      "bbox": [
        1375,
        2526,
        46,
        83
      ],
      "confidence": 41
    },
    {
      "text": "Le",
      "bbox": [
        4959,
        2515,
        78,
        94
      ],
      "confidence": 40
    },
    {
      "text": "Se)",
      "bbox": [
        3246,
        2573,
        185,
        119
      ],
      "confidence": 36
    },
    {
      "text": "|",
      "bbox": [
        1402,
        2668,
        19,
        57
      ],
      "confidence": 74
    },
    {
      "text": "A",
      "bbox": [
        3267,
        2667,
        72,
        72
      ],
      "confidence": 77
    },
    {
      "text": "[0.2",
      "bbox": [
        783,
        2643,
        223,
        160
      ],
      "confidence": 37
    },
    {
      "text": "Z",
      "bbox": [
        3267,
        2736,
        41,
        69
      ],
      "confidence": 83
    },
    {
      "text": "woe",
      "bbox": [
        4337,
        2828,
        107,
        62
      ],
      "confidence": 44
    },
    {
      "text": "oT",
      "bbox": [
        3219,
        2924,
        303,
        47
      ],
      "confidence": 32
    },
    {
      "text": "FRAME",
      "bbox": [
        8583,
        2896,
        185,
        43
      ],
      "confidence": 85
    },
    {
      "text": "}",
      "bbox": [
        1513,
        3023,
        16,
        36
      ],
      "confidence": 48
    },
    {
      "text": "re",
      "bbox": [
        4850,
        2995,
        319,
        103
      ],
      "confidence": 51
    },
    {
      "text": "aS",
      "bbox": [
        5872,
        2954,
        571,
        148
      ],
      "confidence": 34
    },
    {
      "text": "i",
      "bbox": [
        1480,
        3122,
        48,
        77
      ],
      "confidence": 70
    },
    {
      "text": "=",
      "bbox": [
        2509,
        3124,
        32,
        41
      ],
      "confidence": 59
    },
    {
      "text": ")",
      "bbox": [
        4850,
        3098,
        20,
        78
      ],
      "confidence": 48
    },
    {
      "text": "\\\\",
      "bbox": [
        6458,
        3096,
        56,
        102
      ],
      "confidence": 90
    },
    {
      "text": "-",
      "bbox": [
        196,
        3202,
        15,
        31
      ],
      "confidence": 38
    },
    {
      "text": "a",
      "bbox": [
        1541,
        3152,
        101,
        111
      ],
      "confidence": 39
    },
    {
      "text": "x",
      "bbox": [
        2267,
        3171,
        31,
        42
      ],
      "confidence": 31
    },
    {
      "text": "si,",
      "bbox": [
        6494,
        3183,
        239,
        70
      ],
      "confidence": 37
    },
    {
      "text": "F",
      "bbox": [
        9838,
        3189,
        16,
        30
      ],
      "confidence": 91
    },
    {
      "text": "Hf",
      "bbox": [
        1442,
        3224,
        46,
        85
      ],
      "confidence": 58
    },
    {
      "text": "RE",
      "bbox": [
        2409,
        3195,
        132,
        146
      ],
      "confidence": 49
    },
    {
      "text": "U",
      "bbox": [
        5765,
        3286,
        39,
        18
      ],
      "confidence": 54
    },
    {
      "text": "/f",
      "bbox": [
        1397,
        3268,
        72,
        144
      ],
      "confidence": 56
    },
    {
      "text": "\\",
      "bbox": [
        1591,
        3340,
        21,
        80
      ],
      "confidence": 31
    },
    {
      "text": "y",
      "bbox": [
        6458,
        3299,
        55,
        119
      ],
      "confidence": 88
    },
    {
      "text": ".",
      "bbox": [
        1223,
        3377,
        5,
        5
      ],
      "confidence": 51
    },
    {
      "text": "VA",
      "bbox": [
        1388,
        3389,
        46,
        14
      ],
      "confidence": 77
    },
    {
      "text": "G",
      "bbox": [
        1109,
        3431,
        24,
        38
      ],
      "confidence": 63
    },
    {
      "text": "O",
      "bbox": [
        1184,
        3399,
        44,
        65
      ],
      "confidence": 31
    },
    {
      "text": "\\",
      "bbox": [
        1421,
        3395,
        17,
        46
      ],
      "confidence": 93
    },
    {
      "text": "A",
      "bbox": [
        1975,
        3425,
        54,
        72
      ],
      "confidence": 80
    },
    {
      "text": "//",
      "bbox": [
        3002,
        3388,
        40,
        85
      ],
      "confidence": 77
    },
    {
      "text": "alu",
      "bbox": [
        3693,
        3444,
        130,
        28
      ],
      "confidence": 35
    },
    {
      "text": "Cw",
      "bbox": [
        4311,
        3352,
        216,
        136
      ],
      "confidence": 59
    },
    {
      "text": "i",
      "bbox": [
        1549,
        3454,
        48,
        77
      ],
      "confidence": 81
    },
    {
      "text": "=",
      "bbox": [
        3966,
        3478,
        164,
        81
      ],
      "confidence": 78
    },
    {
      "text": "A\\",
      "bbox": [
        4915,
        3463,
        62,
        110
      ],
      "confidence": 31
    },
    {
      "text": "a",
      "bbox": [
        5908,
        3449,
        137,
        69
      ],
      "confidence": 44
    },
    {
      "text": "VY",
      "bbox": [
        1469,
        3480,
        106,
        156
      ],
      "confidence": 39
    },
    {
      "text": "KAT)",
      "bbox": [
        3962,
        3534,
        168,
        112
      ],
      "confidence": 36
    },
    {
      "text": "acl",
      "bbox": [
        5169,
        3508,
        164,
        134
      ],
      "confidence": 34
    },
    {
      "text": "L",
      "bbox": [
        1208,
        3651,
        41,
        67
      ],
      "confidence": 83
    },
    {
      "text": "BI",
      "bbox": [
        1928,
        3644,
        86,
        107
      ],
      "confidence": 69
    },
    {
      "text": ">",
      "bbox": [
        3064,
        3629,
        51,
        23
      ],
      "confidence": 75
    },
    {
      "text": "Ks",
      "bbox": [
        3796,
        3682,
        140,
        43
      ],
      "confidence": 89
    },
    {
      "text": "i=",
      "bbox": [
        4582,
        3612,
        114,
        120
      ],
      "confidence": 61
    },
    {
      "text": "\\\\",
      "bbox": [
        4849,
        3626,
        54,
        134
      ],
      "confidence": 76
    },
    {
      "text": "AS",
      "bbox": [
        4983,
        3577,
        145,
        143
      ],
      "confidence": 56
    },
    {
      "text": "|",
      "bbox": [
        5852,
        3669,
        2,
        37
      ],
      "confidence": 80
    },
    {
      "text": "=",
      "bbox": [
        3982,
        3741,
        41,
        26
      ],
      "confidence": 56
    },
    {
      "text": "+h",
      "bbox": [
        4858,
        3758,
        74,
        109
      ],
      "confidence": 76
    },
    {
      "text": ">.",
      "bbox": [
        6407,
        3767,
        38,
        37
      ],
      "confidence": 38
    },
    {
      "text": "G",
      "bbox": [
        9836,
        3762,
        18,
        31
      ],
      "confidence": 35
    },
    {
      "text": "N",
      "bbox": [
        399,
        3902,
        23,
        31
      ],
      "confidence": 69
    },
    {
      "text": "e+",
      "bbox": [
        4685,
        3805,
        218,
        137
      ],
      "confidence": 43
    },
    {
      "text": "an",
      "bbox": [
        3213,
        3909,
        54,
        56
      ],
      "confidence": 56
    },
    {
      "text": "AK",
      "bbox": [
        3496,
        3908,
        190,
        65
      ],
      "confidence": 39
    },
    {
      "text": "=",
      "bbox": [
        1292,
        3938,
        106,
        69
      ],
      "confidence": 67
    },
    {
      "text": "ae",
      "bbox": [
        3089,
        3938,
        563,
        140
      ],
      "confidence": 37
    },
    {
      "text": "Ks",
      "bbox": [
        1481,
        4051,
        45,
        73
      ],
      "confidence": 53
    },
    {
      "text": "SoS",
      "bbox": [
        1782,
        4080,
        164,
        50
      ],
      "confidence": 39
    },
    {
      "text": "Ou",
      "bbox": [
        4080,
        4072,
        36,
        73
      ],
      "confidence": 50
    },
    {
      "text": "[25\"]",
      "bbox": [
        4561,
        4114,
        159,
        119
      ],
      "confidence": 68
    },
    {
      "text": "\\",
      "bbox": [
        3624,
        4184,
        15,
        72
      ],
      "confidence": 53
    },
    {
      "text": "|",
      "bbox": [
        4111,
        4184,
        94,
        49
      ],
      "confidence": 39
    },
    {
      "text": "C",
      "bbox": [
        2680,
        4263,
        24,
        38
      ],
      "confidence": 33
    },
    {
      "text": "=",
      "bbox": [
        3712,
        4273,
        53,
        73
      ],
      "confidence": 60
    },
    {
      "text": "Zz",
      "bbox": [
        2673,
        4305,
        31,
        24
      ],
      "confidence": 48
    },
    {
      "text": "H",
      "bbox": [
        195,
        4363,
        17,
        30
      ],
      "confidence": 84
    },
    {
      "text": "H",
      "bbox": [
        9832,
        4362,
        17,
        29
      ],
      "confidence": 88
    },
    {
      "text": "Alas",
      "bbox": [
        1763,
        4391,
        221,
        100
      ],
      "confidence": 41
    },
    {
      "text": "a",
      "bbox": [
        2672,
        4408,
        163,
        80
      ],
      "confidence": 72
    },
    {
      "text": "BS)",
      "bbox": [
        2672,
        4471,
        161,
        104
      ],
      "confidence": 40
    },
    {
      "text": "AGREEMENT.",
      "bbox": [
        8027,
        4484,
        193,
        31
      ],
      "confidence": 80
    },
    {
      "text": "DEL_No.",
      "bbox": [
        698,
        4868,
        245,
        43
      ],
      "confidence": 63
    },
    {
      "text": "K",
      "bbox": [
        3365,
        4872,
        54,
        73
      ],
      "confidence": 79
    },
    {
      "text": "J",
      "bbox": [
        198,
        4939,
        13,
        30
      ],
      "confidence": 96
    },
    {
      "text": "J",
      "bbox": [
        9837,
        4929,
        13,
        31
      ],
      "confidence": 94
    },
    {
      "text": "ro)",
      "bbox": [
        969,
        4969,
        101,
        60
      ],
      "confidence": 39
    },
    {
      "text": ">",
      "bbox": [
        6954,
        4984,
        64,
        60
      ],
      "confidence": 86
    },
    {
      "text": "Lh",
      "bbox": [
        6874,
        5019,
        124,
        124
      ],
      "confidence": 33
    },
    {
      "text": "\\",
      "bbox": [
        6971,
        5138,
        81,
        162
      ],
      "confidence": 87
    },
    {
      "text": "DELNo",
      "bbox": [
        2787,
        5446,
        225,
        44
      ],
      "confidence": 40
    },
    {
      "text": "AaB",
      "bbox": [
        5685,
        5409,
        203,
        43
      ],
      "confidence": 50
    },
    {
      "text": "an",
      "bbox": [
        197,
        5492,
        106,
        76
      ],
      "confidence": 34
    },
    {
      "text": "F",
      "bbox": [
        1180,
        5533,
        31,
        42
      ],
      "confidence": 70
    },
    {
      "text": "fee",
      "bbox": [
        5179,
        5512,
        233,
        132
      ],
      "confidence": 48
    },
    {
      "text": "\\",
      "bbox": [
        6977,
        5535,
        103,
        162
      ],
      "confidence": 79
    },
    {
      "text": "THIS",
      "bbox": [
        7867,
        5591,
        56,
        22
      ],
      "confidence": 96
    },
    {
      "text": "Wk",
      "bbox": [
        1034,
        5599,
        172,
        124
      ],
      "confidence": 37
    },
    {
      "text": "VA",
      "bbox": [
        4866,
        5624,
        89,
        107
      ],
      "confidence": 41
    },
    {
      "text": "SF",
      "bbox": [
        3005,
        5718,
        791,
        125
      ],
      "confidence": 34
    },
    {
      "text": "Oy",
      "bbox": [
        4720,
        5719,
        165,
        78
      ],
      "confidence": 59
    },
    {
      "text": "\\),",
      "bbox": [
        7066,
        5685,
        64,
        136
      ],
      "confidence": 51
    },
    {
      "text": "=",
      "bbox": [
        6651,
        5825,
        113,
        25
      ],
      "confidence": 74
    },
    {
      "text": "<<",
      "bbox": [
        1272,
        5876,
        197,
        90
      ],
      "confidence": 42
    },
    {
      "text": "(",
      "bbox": [
        4825,
        5826,
        26,
        109
      ],
      "confidence": 89
    },
    {
      "text": "Ww",
      "bbox": [
        6755,
        5835,
        242,
        155
      ],
      "confidence": 65
    },
    {
      "text": "an",
      "bbox": [
        701,
        5862,
        190,
        171
      ],
      "confidence": 49
    },
    {
      "text": "US",
      "bbox": [
        1152,
        5861,
        290,
        134
      ],
      "confidence": 39
    },
    {
      "text": "No",
      "bbox": [
        3702,
        5967,
        53,
        48
      ],
      "confidence": 77
    },
    {
      "text": "[]",
      "bbox": [
        5249,
        5946,
        39,
        60
      ],
      "confidence": 77
    },
    {
      "text": "Autol",
      "bbox": [
        7786,
        5881,
        425,
        129
      ],
      "confidence": 88
    },
    {
      "text": "iV",
      "bbox": [
        8232,
        5926,
        131,
        78
      ],
      "confidence": 89
    },
    {
      "text": "Wie",
      "bbox": [
        515,
        5990,
        173,
        144
      ],
      "confidence": 63
    },
    {
      "text": "Qo",
      "bbox": [
        3634,
        5994,
        80,
        71
      ],
      "confidence": 50
    },
    {
      "text": "A",
      "bbox": [
        3950,
        6035,
        43,
        27
      ],
      "confidence": 59
    },
    {
      "text": "Germany",
      "bbox": [
        8737,
        6009,
        148,
        39
      ],
      "confidence": 91
    },
    {
      "text": "\\",
      "bbox": [
        1393,
        6181,
        27,
        49
      ],
      "confidence": 83
    },
    {
      "text": "SCALE",
      "bbox": [
        9542,
        6194,
        105,
        31
      ],
      "confidence": 95
    },
    {
      "text": "H",
      "bbox": [
        944,
        6211,
        30,
        41
      ],
      "confidence": 84
    },
    {
      "text": "eS",
      "bbox": [
        1412,
        6170,
        403,
        375
      ],
      "confidence": 40
    },
    {
      "text": "a",
      "bbox": [
        3896,
        6202,
        97,
        108
      ],
      "confidence": 44
    },
    {
      "text": "CUSTOMER",
      "bbox": [
        7723,
        6312,
        172,
        32
      ],
      "confidence": 96
    },
    {
      "text": "aah",
      "bbox": [
        9542,
        6430,
        128,
        32
      ],
      "confidence": 32
    },
    {
      "text": "TRACEABILITY",
      "bbox": [
        7724,
        6666,
        260,
        32
      ],
      "confidence": 78
    },
    {
      "text": "REVISTON",
      "bbox": [
        9542,
        6666,
        172,
        32
      ],
      "confidence": 86
    },
    {
      "text": "/|",
      "bbox": [
        9158,
        6750,
        39,
        92
      ],
      "confidence": 63
    },
    {
      "text": "()",
      "bbox": [
        9653,
        6765,
        35,
        93
      ],
      "confidence": 76
    },
    {
      "text": "pt",
      "bbox": [
        835,
        6900,
        8263,
        56
      ],
      "confidence": 33
    }
  ]
}